<?xml version='1.0' encoding='utf-8'?>
<!DOCTYPE LIGO_LW SYSTEM "http://ldas-sw.ligo.caltech.edu/doc/ligolwAPI/html/ligolw_dtd.txt">
<LIGO_LW>
	<Table Name="process:table">
		<Column Type="lstring" Name="process:comment"/>
		<Column Type="lstring" Name="process:node"/>
		<Column Type="lstring" Name="process:domain"/>
		<Column Type="int_4s" Name="process:unix_procid"/>
		<Column Type="int_4s" Name="process:start_time"/>
		<Column Type="ilwd:char" Name="process:process_id"/>
		<Column Type="int_4s" Name="process:is_online"/>
		<Column Type="lstring" Name="process:ifos"/>
		<Column Type="int_4s" Name="process:jobid"/>
		<Column Type="lstring" Name="process:username"/>
		<Column Type="lstring" Name="process:program"/>
		<Column Type="int_4s" Name="process:end_time"/>
		<Column Type="lstring" Name="process:version"/>
		<Column Type="lstring" Name="process:cvs_repository"/>
		<Column Type="int_4s" Name="process:cvs_entry_time"/>
		<Stream Delimiter="," Type="Local" Name="process:table">
			,"ldas-grid",,2030317,1167239787,"process:process_id:0",0,,0,"bhughey","ligolw-vetodef-create",,"0.1",,,
			,"ldas-grid",,2030463,1167239787,"process:process_id:1",0,,0,"bhughey","ligolw-vetodef-append",,,,,
			,"ldas-grid",,2030699,1167239787,"process:process_id:2",0,,0,"bhughey","ligolw-vetodef-append",,,,,
			,"ldas-grid",,2030861,1167239788,"process:process_id:3",0,,0,"bhughey","ligolw-vetodef-append",,,,,
			,"ldas-grid",,2031051,1167239788,"process:process_id:4",0,,0,"bhughey","ligolw-vetodef-append",,,,,
			,"ldas-grid",,2031228,1167239788,"process:process_id:5",0,,0,"bhughey","ligolw-vetodef-append",,,,,
			,"ldas-grid",,2031397,1167239788,"process:process_id:6",0,,0,"bhughey","ligolw-vetodef-append",,,,,
			,"ldas-grid",,2031587,1167239789,"process:process_id:7",0,,0,"bhughey","ligolw-vetodef-append",,,,,
			,"ldas-grid",,2031805,1167239789,"process:process_id:8",0,,0,"bhughey","ligolw-vetodef-append",,,,,
			,"ldas-grid",,2031988,1167239789,"process:process_id:9",0,,0,"bhughey","ligolw-vetodef-append",,,,,
			,"ldas-grid",,2032185,1167239790,"process:process_id:10",0,,0,"bhughey","ligolw-vetodef-append",,,,,
			,"ldas-grid",,2032355,1167239790,"process:process_id:11",0,,0,"bhughey","ligolw-vetodef-append",,,,,
			,"ldas-grid",,2032552,1167239790,"process:process_id:12",0,,0,"bhughey","ligolw-vetodef-append",,,,,
			,"ldas-grid",,2032729,1167239790,"process:process_id:13",0,,0,"bhughey","ligolw-vetodef-append",,,,,
			,"ldas-grid",,2032918,1167239791,"process:process_id:14",0,,0,"bhughey","ligolw-vetodef-append",,,,,
			,"ldas-grid",,2033118,1167239791,"process:process_id:15",0,,0,"bhughey","ligolw-vetodef-append",,,,,
			,"ldas-grid",,2033306,1167239791,"process:process_id:16",0,,0,"bhughey","ligolw-vetodef-append",,,,,
			,"ldas-grid",,2033476,1167239792,"process:process_id:17",0,,0,"bhughey","ligolw-vetodef-append",,,,,
			,"ldas-grid",,2033669,1167239792,"process:process_id:18",0,,0,"bhughey","ligolw-vetodef-append",,,,,
			,"ldas-grid",,2033746,1167239792,"process:process_id:19",0,,0,"bhughey","ligolw-vetodef-append",,,,,
			,"ldas-grid",,2033752,1167239792,"process:process_id:20",0,,0,"bhughey","ligolw-vetodef-append",,,,,
			,"ldas-grid",,2033753,1167239793,"process:process_id:21",0,,0,"bhughey","ligolw-vetodef-append",,,,,
		</Stream>
	</Table>
	<Table Name="process_params:table">
		<Column Type="ilwd:char" Name="process_params:process_id"/>
		<Column Type="lstring" Name="process_params:program"/>
		<Column Type="lstring" Name="process_params:type"/>
		<Column Type="lstring" Name="process_params:value"/>
		<Column Type="lstring" Name="process_params:param"/>
		<Stream Delimiter="," Type="Local" Name="process_params:table">
			"process:process_id:0","ligolw-vetodef-create","lstring","H1L1-HOFT_C00_O2_BURST.xml","output-file",
			"process:process_id:0","ligolw-vetodef-create",,,"--force",
			"process:process_id:1","ligolw-vetodef-append","lstring","H1L1-HOFT_C00_O2_BURST.xml","",
			"process:process_id:1","ligolw-vetodef-append","int_8s","1","--category",
			"process:process_id:1","ligolw-vetodef-append","lstring","Missing H1 calibrated h(t) data","--comment",
			"process:process_id:1","ligolw-vetodef-append",,,"--skip-process-tables",
			"process:process_id:1","ligolw-vetodef-append","int_8s","1161907217","--start-time",
			"process:process_id:1","ligolw-vetodef-append","int_8s","0","--end-pad",
			"process:process_id:1","ligolw-vetodef-append","lstring","H1:DCS-MISSING_H1_HOFT_C00:1","--flag",
			"process:process_id:1","ligolw-vetodef-append","int_8s","0","--start-pad",
			"process:process_id:1","ligolw-vetodef-append","int_8s","0","--end-time",
			"process:process_id:1","ligolw-vetodef-append","lstring","https://segments.ligo.org","--segment-url",
			"process:process_id:2","ligolw-vetodef-append","lstring","H1L1-HOFT_C00_O2_BURST.xml","",
			"process:process_id:2","ligolw-vetodef-append","int_8s","1","--category",
			"process:process_id:2","ligolw-vetodef-append","lstring","Missing L1 calibrated h(t) data","--comment",
			"process:process_id:2","ligolw-vetodef-append",,,"--skip-process-tables",
			"process:process_id:2","ligolw-vetodef-append","int_8s","1161907217","--start-time",
			"process:process_id:2","ligolw-vetodef-append","int_8s","0","--end-pad",
			"process:process_id:2","ligolw-vetodef-append","lstring","L1:DCS-MISSING_L1_HOFT_C00:1","--flag",
			"process:process_id:2","ligolw-vetodef-append","int_8s","0","--start-pad",
			"process:process_id:2","ligolw-vetodef-append","int_8s","0","--end-time",
			"process:process_id:2","ligolw-vetodef-append","lstring","https://segments.ligo.org","--segment-url",
			"process:process_id:3","ligolw-vetodef-append","lstring","H1L1-HOFT_C00_O2_BURST.xml","",
			"process:process_id:3","ligolw-vetodef-append","int_8s","1","--category",
			"process:process_id:3","ligolw-vetodef-append","lstring","Stochastic hardware injections","--comment",
			"process:process_id:3","ligolw-vetodef-append",,,"--skip-process-tables",
			"process:process_id:3","ligolw-vetodef-append","int_8s","1161907217","--start-time",
			"process:process_id:3","ligolw-vetodef-append","int_8s","0","--end-pad",
			"process:process_id:3","ligolw-vetodef-append","lstring","H1:ODC-INJECTION_STOCHASTIC:2","--flag",
			"process:process_id:3","ligolw-vetodef-append","int_8s","0","--start-pad",
			"process:process_id:3","ligolw-vetodef-append","int_8s","0","--end-time",
			"process:process_id:3","ligolw-vetodef-append","lstring","https://segments.ligo.org","--segment-url",
			"process:process_id:4","ligolw-vetodef-append","lstring","H1L1-HOFT_C00_O2_BURST.xml","",
			"process:process_id:4","ligolw-vetodef-append","int_8s","1","--category",
			"process:process_id:4","ligolw-vetodef-append","lstring","Stochastic hardware injections","--comment",
			"process:process_id:4","ligolw-vetodef-append",,,"--skip-process-tables",
			"process:process_id:4","ligolw-vetodef-append","int_8s","1161907217","--start-time",
			"process:process_id:4","ligolw-vetodef-append","int_8s","0","--end-pad",
			"process:process_id:4","ligolw-vetodef-append","lstring","L1:ODC-INJECTION_STOCHASTIC:2","--flag",
			"process:process_id:4","ligolw-vetodef-append","int_8s","0","--start-pad",
			"process:process_id:4","ligolw-vetodef-append","int_8s","0","--end-time",
			"process:process_id:4","ligolw-vetodef-append","lstring","https://segments.ligo.org","--segment-url",
			"process:process_id:5","ligolw-vetodef-append","lstring","H1L1-HOFT_C00_O2_BURST.xml","",
			"process:process_id:5","ligolw-vetodef-append","int_8s","4","--category",
			"process:process_id:5","ligolw-vetodef-append","lstring","CBC hardware injections","--comment",
			"process:process_id:5","ligolw-vetodef-append",,,"--skip-process-tables",
			"process:process_id:5","ligolw-vetodef-append","int_8s","1161907217","--start-time",
			"process:process_id:5","ligolw-vetodef-append","int_8s","8","--end-pad",
			"process:process_id:5","ligolw-vetodef-append","lstring","H1:ODC-INJECTION_CBC:2","--flag",
			"process:process_id:5","ligolw-vetodef-append","int_8s","-8","--start-pad",
			"process:process_id:5","ligolw-vetodef-append","int_8s","0","--end-time",
			"process:process_id:5","ligolw-vetodef-append","lstring","https://segments.ligo.org","--segment-url",
			"process:process_id:6","ligolw-vetodef-append","lstring","H1L1-HOFT_C00_O2_BURST.xml","",
			"process:process_id:6","ligolw-vetodef-append","int_8s","4","--category",
			"process:process_id:6","ligolw-vetodef-append","lstring","CBC hardware injections","--comment",
			"process:process_id:6","ligolw-vetodef-append",,,"--skip-process-tables",
			"process:process_id:6","ligolw-vetodef-append","int_8s","1161907217","--start-time",
			"process:process_id:6","ligolw-vetodef-append","int_8s","8","--end-pad",
			"process:process_id:6","ligolw-vetodef-append","lstring","L1:ODC-INJECTION_CBC:2","--flag",
			"process:process_id:6","ligolw-vetodef-append","int_8s","-8","--start-pad",
			"process:process_id:6","ligolw-vetodef-append","int_8s","0","--end-time",
			"process:process_id:6","ligolw-vetodef-append","lstring","https://segments.ligo.org","--segment-url",
			"process:process_id:7","ligolw-vetodef-append","lstring","H1L1-HOFT_C00_O2_BURST.xml","",
			"process:process_id:7","ligolw-vetodef-append","int_8s","4","--category",
			"process:process_id:7","ligolw-vetodef-append","lstring","Detchar hardware injection","--comment",
			"process:process_id:7","ligolw-vetodef-append",,,"--skip-process-tables",
			"process:process_id:7","ligolw-vetodef-append","int_8s","1161907217","--start-time",
			"process:process_id:7","ligolw-vetodef-append","int_8s","16","--end-pad",
			"process:process_id:7","ligolw-vetodef-append","lstring","H1:ODC-INJECTION_DETCHAR:2","--flag",
			"process:process_id:7","ligolw-vetodef-append","int_8s","-16","--start-pad",
			"process:process_id:7","ligolw-vetodef-append","int_8s","0","--end-time",
			"process:process_id:7","ligolw-vetodef-append","lstring","https://segments.ligo.org","--segment-url",
			"process:process_id:8","ligolw-vetodef-append","lstring","H1L1-HOFT_C00_O2_BURST.xml","",
			"process:process_id:8","ligolw-vetodef-append","int_8s","4","--category",
			"process:process_id:8","ligolw-vetodef-append","lstring","Detchar hardware injection","--comment",
			"process:process_id:8","ligolw-vetodef-append",,,"--skip-process-tables",
			"process:process_id:8","ligolw-vetodef-append","int_8s","1161907217","--start-time",
			"process:process_id:8","ligolw-vetodef-append","int_8s","16","--end-pad",
			"process:process_id:8","ligolw-vetodef-append","lstring","L1:ODC-INJECTION_DETCHAR:2","--flag",
			"process:process_id:8","ligolw-vetodef-append","int_8s","-16","--start-pad",
			"process:process_id:8","ligolw-vetodef-append","int_8s","0","--end-time",
			"process:process_id:8","ligolw-vetodef-append","lstring","https://segments.ligo.org","--segment-url",
			"process:process_id:9","ligolw-vetodef-append","lstring","H1L1-HOFT_C00_O2_BURST.xml","",
			"process:process_id:9","ligolw-vetodef-append","int_8s","4","--category",
			"process:process_id:9","ligolw-vetodef-append","lstring","Burst hardware injections","--comment",
			"process:process_id:9","ligolw-vetodef-append",,,"--skip-process-tables",
			"process:process_id:9","ligolw-vetodef-append","int_8s","1161907217","--start-time",
			"process:process_id:9","ligolw-vetodef-append","int_8s","4","--end-pad",
			"process:process_id:9","ligolw-vetodef-append","lstring","H1:ODC-INJECTION_BURST:2","--flag",
			"process:process_id:9","ligolw-vetodef-append","int_8s","-4","--start-pad",
			"process:process_id:9","ligolw-vetodef-append","int_8s","0","--end-time",
			"process:process_id:9","ligolw-vetodef-append","lstring","https://segments.ligo.org","--segment-url",
			"process:process_id:10","ligolw-vetodef-append","lstring","H1L1-HOFT_C00_O2_BURST.xml","",
			"process:process_id:10","ligolw-vetodef-append","int_8s","4","--category",
			"process:process_id:10","ligolw-vetodef-append","lstring","Burst hardware injections","--comment",
			"process:process_id:10","ligolw-vetodef-append",,,"--skip-process-tables",
			"process:process_id:10","ligolw-vetodef-append","int_8s","1161907217","--start-time",
			"process:process_id:10","ligolw-vetodef-append","int_8s","4","--end-pad",
			"process:process_id:10","ligolw-vetodef-append","lstring","L1:ODC-INJECTION_BURST:2","--flag",
			"process:process_id:10","ligolw-vetodef-append","int_8s","-4","--start-pad",
			"process:process_id:10","ligolw-vetodef-append","int_8s","0","--end-time",
			"process:process_id:10","ligolw-vetodef-append","lstring","https://segments.ligo.org","--segment-url",
			"process:process_id:11","ligolw-vetodef-append","lstring","H1L1-HOFT_C00_O2_BURST.xml","",
			"process:process_id:11","ligolw-vetodef-append","int_8s","2","--category",
			"process:process_id:11","ligolw-vetodef-append","lstring","Saturations in ETMY ESD drive signal monitored by DMT","--comment",
			"process:process_id:11","ligolw-vetodef-append",,,"--skip-process-tables",
			"process:process_id:11","ligolw-vetodef-append","int_8s","1161907217","--start-time",
			"process:process_id:11","ligolw-vetodef-append","int_8s","1","--end-pad",
			"process:process_id:11","ligolw-vetodef-append","lstring","H1:DMT-ETMY_ESD_DAC_OVERFLOW:1","--flag",
			"process:process_id:11","ligolw-vetodef-append","int_8s","-1","--start-pad",
			"process:process_id:11","ligolw-vetodef-append","int_8s","0","--end-time",
			"process:process_id:11","ligolw-vetodef-append","lstring","https://segments.ligo.org","--segment-url",
			"process:process_id:12","ligolw-vetodef-append","lstring","H1L1-HOFT_C00_O2_BURST.xml","",
			"process:process_id:12","ligolw-vetodef-append","int_8s","2","--category",
			"process:process_id:12","ligolw-vetodef-append","lstring","Saturations in ETMY ESD drive signal monitored by DMT","--comment",
			"process:process_id:12","ligolw-vetodef-append",,,"--skip-process-tables",
			"process:process_id:12","ligolw-vetodef-append","int_8s","1161907217","--start-time",
			"process:process_id:12","ligolw-vetodef-append","int_8s","1","--end-pad",
			"process:process_id:12","ligolw-vetodef-append","lstring","L1:DMT-ETMY_ESD_DAC_OVERFLOW:1","--flag",
			"process:process_id:12","ligolw-vetodef-append","int_8s","-1","--start-pad",
			"process:process_id:12","ligolw-vetodef-append","int_8s","0","--end-time",
			"process:process_id:12","ligolw-vetodef-append","lstring","https://segments.ligo.org","--segment-url",
			"process:process_id:13","ligolw-vetodef-append","lstring","H1L1-HOFT_C00_O2_BURST.xml","",
			"process:process_id:13","ligolw-vetodef-append","int_8s","2","--category",
			"process:process_id:13","ligolw-vetodef-append","lstring","Saturations in ETMX ESD drive signal monitored by DMT","--comment",
			"process:process_id:13","ligolw-vetodef-append",,,"--skip-process-tables",
			"process:process_id:13","ligolw-vetodef-append","int_8s","1161907217","--start-time",
			"process:process_id:13","ligolw-vetodef-append","int_8s","1","--end-pad",
			"process:process_id:13","ligolw-vetodef-append","lstring","H1:DMT-ETMX_ESD_DAC_OVERFLOW:1","--flag",
			"process:process_id:13","ligolw-vetodef-append","int_8s","-1","--start-pad",
			"process:process_id:13","ligolw-vetodef-append","int_8s","0","--end-time",
			"process:process_id:13","ligolw-vetodef-append","lstring","https://segments.ligo.org","--segment-url",
			"process:process_id:14","ligolw-vetodef-append","lstring","H1L1-HOFT_C00_O2_BURST.xml","",
			"process:process_id:14","ligolw-vetodef-append","int_8s","2","--category",
			"process:process_id:14","ligolw-vetodef-append","lstring","Saturations in ETMX ESD drive signal monitored by DMT","--comment",
			"process:process_id:14","ligolw-vetodef-append",,,"--skip-process-tables",
			"process:process_id:14","ligolw-vetodef-append","int_8s","1161907217","--start-time",
			"process:process_id:14","ligolw-vetodef-append","int_8s","1","--end-pad",
			"process:process_id:14","ligolw-vetodef-append","lstring","L1:DMT-ETMX_ESD_DAC_OVERFLOW:1","--flag",
			"process:process_id:14","ligolw-vetodef-append","int_8s","-1","--start-pad",
			"process:process_id:14","ligolw-vetodef-append","int_8s","0","--end-time",
			"process:process_id:14","ligolw-vetodef-append","lstring","https://segments.ligo.org","--segment-url",
			"process:process_id:15","ligolw-vetodef-append","lstring","H1L1-HOFT_C00_O2_BURST.xml","",
			"process:process_id:15","ligolw-vetodef-append","int_8s","2","--category",
			"process:process_id:15","ligolw-vetodef-append","lstring","OMC DCPD_A ADC overflow monitored by DMT","--comment",
			"process:process_id:15","ligolw-vetodef-append",,,"--skip-process-tables",
			"process:process_id:15","ligolw-vetodef-append","int_8s","1161907217","--start-time",
			"process:process_id:15","ligolw-vetodef-append","int_8s","0","--end-pad",
			"process:process_id:15","ligolw-vetodef-append","lstring","H1:DMT-OMC_DCPD_ADC_OVERFLOW:1","--flag",
			"process:process_id:15","ligolw-vetodef-append","int_8s","0","--start-pad",
			"process:process_id:15","ligolw-vetodef-append","int_8s","0","--end-time",
			"process:process_id:15","ligolw-vetodef-append","lstring","https://segments.ligo.org","--segment-url",
			"process:process_id:16","ligolw-vetodef-append","lstring","H1L1-HOFT_C00_O2_BURST.xml","",
			"process:process_id:16","ligolw-vetodef-append","int_8s","2","--category",
			"process:process_id:16","ligolw-vetodef-append","lstring","OMC DCPD_A ADC overflow monitored by DMT","--comment",
			"process:process_id:16","ligolw-vetodef-append",,,"--skip-process-tables",
			"process:process_id:16","ligolw-vetodef-append","int_8s","1161907217","--start-time",
			"process:process_id:16","ligolw-vetodef-append","int_8s","0","--end-pad",
			"process:process_id:16","ligolw-vetodef-append","lstring","L1:DMT-OMC_DCPD_ADC_OVERFLOW:1","--flag",
			"process:process_id:16","ligolw-vetodef-append","int_8s","0","--start-pad",
			"process:process_id:16","ligolw-vetodef-append","int_8s","0","--end-time",
			"process:process_id:16","ligolw-vetodef-append","lstring","https://segments.ligo.org","--segment-url",
			"process:process_id:17","ligolw-vetodef-append","lstring","H1L1-HOFT_C00_O2_BURST.xml","",
			"process:process_id:17","ligolw-vetodef-append","int_8s","1","--category",
			"process:process_id:17","ligolw-vetodef-append","lstring","PCALY is switching on or off","--comment",
			"process:process_id:17","ligolw-vetodef-append",,,"--skip-process-tables",
			"process:process_id:17","ligolw-vetodef-append","int_8s","1161907217","--start-time",
			"process:process_id:17","ligolw-vetodef-append","int_8s","2","--end-pad",
			"process:process_id:17","ligolw-vetodef-append","lstring","H1:DMT-PCALY_STATE_CHANGE:1","--flag",
			"process:process_id:17","ligolw-vetodef-append","int_8s","-2","--start-pad",
			"process:process_id:17","ligolw-vetodef-append","int_8s","0","--end-time",
			"process:process_id:17","ligolw-vetodef-append","lstring","https://segments.ligo.org","--segment-url",
			"process:process_id:18","ligolw-vetodef-append","lstring","H1L1-HOFT_C00_O2_BURST.xml","",
			"process:process_id:18","ligolw-vetodef-append","int_8s","1","--category",
			"process:process_id:18","ligolw-vetodef-append","lstring","PCALY is switching on or off","--comment",
			"process:process_id:18","ligolw-vetodef-append",,,"--skip-process-tables",
			"process:process_id:18","ligolw-vetodef-append","int_8s","1161907217","--start-time",
			"process:process_id:18","ligolw-vetodef-append","int_8s","2","--end-pad",
			"process:process_id:18","ligolw-vetodef-append","lstring","L1:DMT-PCALY_STATE_CHANGE:1","--flag",
			"process:process_id:18","ligolw-vetodef-append","int_8s","-2","--start-pad",
			"process:process_id:18","ligolw-vetodef-append","int_8s","0","--end-time",
			"process:process_id:18","ligolw-vetodef-append","lstring","https://segments.ligo.org","--segment-url",
			"process:process_id:19","ligolw-vetodef-append","lstring","H1L1-HOFT_C00_O2_BURST.xml","",
			"process:process_id:19","ligolw-vetodef-append","int_8s","2","--category",
			"process:process_id:19","ligolw-vetodef-append","lstring","60 Hz periodic power supply glitching in end-Y station during late ER10","--comment",
			"process:process_id:19","ligolw-vetodef-append",,,"--skip-process-tables",
			"process:process_id:19","ligolw-vetodef-append","int_8s","1161907217","--start-time",
			"process:process_id:19","ligolw-vetodef-append","int_8s","0","--end-pad",
			"process:process_id:19","ligolw-vetodef-append","lstring","L1:DCH-60HZ_EY_PERIODIC_GLITCHING:1","--flag",
			"process:process_id:19","ligolw-vetodef-append","int_8s","0","--start-pad",
			"process:process_id:19","ligolw-vetodef-append","int_8s","1164556817","--end-time",
			"process:process_id:19","ligolw-vetodef-append","lstring","https://segments.ligo.org","--segment-url",
			"process:process_id:20","ligolw-vetodef-append","lstring","H1L1-HOFT_C00_O2_BURST.xml","",
			"process:process_id:20","ligolw-vetodef-append","int_8s","2","--category",
			"process:process_id:20","ligolw-vetodef-append","lstring","RF beatnotes on December 15th","--comment",
			"process:process_id:20","ligolw-vetodef-append",,,"--skip-process-tables",
			"process:process_id:20","ligolw-vetodef-append","int_8s","1165795217","--start-time",
			"process:process_id:20","ligolw-vetodef-append","int_8s","0","--end-pad",
			"process:process_id:20","ligolw-vetodef-append","lstring","L1:DCH-DEC15_WHISTLES:1","--flag",
			"process:process_id:20","ligolw-vetodef-append","int_8s","0","--start-pad",
			"process:process_id:20","ligolw-vetodef-append","int_8s","1165881617","--end-time",
			"process:process_id:20","ligolw-vetodef-append","lstring","https://segments.ligo.org","--segment-url",
			"process:process_id:21","ligolw-vetodef-append","lstring","H1L1-HOFT_C00_O2_BURST.xml","",
			"process:process_id:21","ligolw-vetodef-append","int_8s","1","--category",
			"process:process_id:21","ligolw-vetodef-append","lstring","High violin modes causing constant OMC DCPD saturations","--comment",
			"process:process_id:21","ligolw-vetodef-append",,,"--skip-process-tables",
			"process:process_id:21","ligolw-vetodef-append","int_8s","1164774480","--start-time",
			"process:process_id:21","ligolw-vetodef-append","int_8s","0","--end-pad",
			"process:process_id:21","ligolw-vetodef-append","lstring","L1:DCH-HIGH_VIOLINS:1","--flag",
			"process:process_id:21","ligolw-vetodef-append","int_8s","0","--start-pad",
			"process:process_id:21","ligolw-vetodef-append","int_8s","1164776579","--end-time",
			"process:process_id:21","ligolw-vetodef-append","lstring","https://segments.ligo.org","--segment-url"
		</Stream>
	</Table>
	<Table Name="veto_definer:table">
		<Column Type="int_4s" Name="veto_definer:category"/>
		<Column Type="lstring" Name="veto_definer:comment"/>
		<Column Type="int_4s" Name="veto_definer:end_pad"/>
		<Column Type="ilwd:char" Name="veto_definer:process_id"/>
		<Column Type="lstring" Name="veto_definer:name"/>
		<Column Type="int_4s" Name="veto_definer:version"/>
		<Column Type="int_4s" Name="veto_definer:start_pad"/>
		<Column Type="int_4s" Name="veto_definer:start_time"/>
		<Column Type="lstring" Name="veto_definer:ifo"/>
		<Column Type="int_4s" Name="veto_definer:end_time"/>
		<Stream Delimiter="," Type="Local" Name="veto_definer:table">
			1,"Missing H1 calibrated h(t) data",0,"process:process_id:1","DCS-MISSING_H1_HOFT_C00",1,0,1161907217,"H1",0,
			1,"Missing L1 calibrated h(t) data",0,"process:process_id:2","DCS-MISSING_L1_HOFT_C00",1,0,1161907217,"L1",0,
			1,"Stochastic hardware injections",0,"process:process_id:3","ODC-INJECTION_STOCHASTIC",2,0,1161907217,"H1",0,
			1,"Stochastic hardware injections",0,"process:process_id:4","ODC-INJECTION_STOCHASTIC",2,0,1161907217,"L1",0,
			4,"CBC hardware injections",8,"process:process_id:5","ODC-INJECTION_CBC",2,-8,1161907217,"H1",0,
			4,"CBC hardware injections",8,"process:process_id:6","ODC-INJECTION_CBC",2,-8,1161907217,"L1",0,
			4,"Detchar hardware injection",16,"process:process_id:7","ODC-INJECTION_DETCHAR",2,-16,1161907217,"H1",0,
			4,"Detchar hardware injection",16,"process:process_id:8","ODC-INJECTION_DETCHAR",2,-16,1161907217,"L1",0,
			4,"Burst hardware injections",4,"process:process_id:9","ODC-INJECTION_BURST",2,-4,1161907217,"H1",0,
			4,"Burst hardware injections",4,"process:process_id:10","ODC-INJECTION_BURST",2,-4,1161907217,"L1",0,
			2,"Saturations in ETMY ESD drive signal monitored by DMT",1,"process:process_id:11","DMT-ETMY_ESD_DAC_OVERFLOW",1,-1,1161907217,"H1",0,
			2,"Saturations in ETMY ESD drive signal monitored by DMT",1,"process:process_id:12","DMT-ETMY_ESD_DAC_OVERFLOW",1,-1,1161907217,"L1",0,
			2,"Saturations in ETMX ESD drive signal monitored by DMT",1,"process:process_id:13","DMT-ETMX_ESD_DAC_OVERFLOW",1,-1,1161907217,"H1",0,
			2,"Saturations in ETMX ESD drive signal monitored by DMT",1,"process:process_id:14","DMT-ETMX_ESD_DAC_OVERFLOW",1,-1,1161907217,"L1",0,
			2,"OMC DCPD_A ADC overflow monitored by DMT",0,"process:process_id:15","DMT-OMC_DCPD_ADC_OVERFLOW",1,0,1161907217,"H1",0,
			2,"OMC DCPD_A ADC overflow monitored by DMT",0,"process:process_id:16","DMT-OMC_DCPD_ADC_OVERFLOW",1,0,1161907217,"L1",0,
			1,"PCALY is switching on or off",2,"process:process_id:17","DMT-PCALY_STATE_CHANGE",1,-2,1161907217,"H1",0,
			1,"PCALY is switching on or off",2,"process:process_id:18","DMT-PCALY_STATE_CHANGE",1,-2,1161907217,"L1",0,
			2,"60 Hz periodic power supply glitching in end-Y station during late ER10",0,"process:process_id:19","DCH-60HZ_EY_PERIODIC_GLITCHING",1,0,1161907217,"L1",1164556817,
			2,"RF beatnotes on December 15th",0,"process:process_id:20","DCH-DEC15_WHISTLES",1,0,1165795217,"L1",1165881617,
			1,"High violin modes causing constant OMC DCPD saturations",0,"process:process_id:21","DCH-HIGH_VIOLINS",1,0,1164774480,"L1",1164776579
		</Stream>
	</Table>
</LIGO_LW>
